widecity_extracter/__init__.py
widecity_extracter/text_extracter.py
widecity_extracter-0.0.2.dist-info/LICENSE
widecity_extracter-0.0.2.dist-info/METADATA
widecity_extracter-0.0.2.dist-info/WHEEL
widecity_extracter-0.0.2.dist-info/top_level.txt
widecity_extracter-0.0.2.dist-info/RECORD
