Metadata-Version: 2.1
Name: widecity-extracter
Version: 0.0.2
Summary: a simple package to extract text from  bills.
Home-page: https://github.com/pypa/sampleproject
Author: amal benny
Author-email: widecity.official@gmail.com
Project-URL: Bug Tracker, https://github.com/pypa/sampleproject/issues
Classifier: Programming Language :: Python :: 3
Classifier: License :: OSI Approved :: MIT License
Classifier: Operating System :: OS Independent
Requires-Python: >=3.7
License-File: LICENSE
